{"version":1,"chords":[{"notes":[0,1,0,1,1,0],"inversion":2,"playability":3,"extras":3},{"notes":[6,5,6,5,5,8],"inversion":4,"playability":3,"extras":1},{"notes":[6,7,6,7,9,8],"inversion":4,"playability":3,"extras":3},{"notes":[12,13,12,13,13,12],"inversion":2,"playability":3,"extras":3},{"notes":[18,17,18,17,17,20],"inversion":4,"playability":3,"extras":1},{"notes":[18,19,18,19,21,20],"inversion":4,"playability":3,"extras":3},{"notes":[4,3,6,7,5,6],"inversion":3,"playability":4,"extras":3},{"notes":[4,5,8,5,5,4],"inversion":3,"playability":4,"extras":1},{"notes":[4,5,6,5,5,6],"inversion":3,"playability":4,"extras":3},{"notes":[6,5,6,5,5,4],"inversion":4,"playability":4,"extras":1},{"notes":[6,5,6,5,5,6],"inversion":4,"playability":4,"extras":1},{"notes":[6,5,8,9,9,8],"inversion":4,"playability":4,"extras":3},{"notes":[6,7,10,9,9,10],"inversion":4,"playability":4,"extras":3},{"notes":[6,7,8,7,9,8],"inversion":4,"playability":4,"extras":3},{"notes":[8,7,8,9,9,10],"inversion":1,"playability":4,"extras":3},{"notes":[8,11,8,9,9,10],"inversion":1,"playability":4,"extras":0},{"notes":[10,11,8,9,9,8],"inversion":5,"playability":4,"extras":0},{"notes":[12,11,12,15,13,12],"inversion":2,"playability":4,"extras":1},{"notes":[16,15,18,19,17,18],"inversion":3,"playability":4,"extras":3},{"notes":[16,17,20,17,17,16],"inversion":3,"playability":4,"extras":1},{"notes":[16,17,18,17,17,18],"inversion":3,"playability":4,"extras":3},{"notes":[18,17,18,17,17,16],"inversion":4,"playability":4,"extras":1},{"notes":[18,17,18,17,17,18],"inversion":4,"playability":4,"extras":1},{"notes":[18,17,20,21,21,20],"inversion":4,"playability":4,"extras":3},{"notes":[18,19,20,19,21,20],"inversion":4,"playability":4,"extras":3},{"notes":[0,1,0,1,1,4],"inversion":2,"playability":5,"extras":1},{"notes":[6,7,10,7,9,6],"inversion":4,"playability":5,"extras":1},{"notes":[12,11,10,9,11,10],"inversion":2,"playability":5,"extras":0},{"notes":[12,13,10,9,9,10],"inversion":2,"playability":5,"extras":0},{"notes":[10,11,10,9,11,10],"inversion":5,"playability":5,"extras":0},{"notes":[12,13,12,13,13,16],"inversion":2,"playability":5,"extras":1},{"notes":[4,1,0,1,1,0],"inversion":3,"playability":6,"extras":1},{"notes":[4,3,2,3,3,6],"inversion":3,"playability":6,"extras":0},{"notes":[4,3,2,3,3,4],"inversion":3,"playability":6,"extras":1},{"notes":[6,3,2,3,3,4],"inversion":4,"playability":6,"extras":1},{"notes":[8,7,6,7,5,6],"inversion":1,"playability":6,"extras":1},{"notes":[8,5,6,5,5,6],"inversion":1,"playability":6,"extras":1},{"notes":[16,13,12,13,13,12],"inversion":3,"playability":6,"extras":1},{"notes":[16,15,14,15,15,18],"inversion":3,"playability":6,"extras":0},{"notes":[16,15,14,15,15,16],"inversion":3,"playability":6,"extras":1},{"notes":[18,15,14,15,15,16],"inversion":4,"playability":6,"extras":1},{"notes":[20,19,18,19,17,18],"inversion":1,"playability":6,"extras":1},{"notes":[20,17,18,17,17,18],"inversion":1,"playability":6,"extras":1},{"notes":[4,5,8,5,5,6],"inversion":3,"playability":7,"extras":1},{"notes":[6,7,6,7,5,8],"inversion":4,"playability":7,"extras":0},{"notes":[6,5,6,7,5,8],"inversion":4,"playability":7,"extras":1},{"notes":[8,7,6,7,9,6],"inversion":1,"playability":7,"extras":0},{"notes":[6,7,10,7,9,8],"inversion":4,"playability":7,"extras":1}]}