{"version":1,"chords":[{"notes":[10,10,14,14,14,10],"inversion":5,"playability":1,"extras":2},{"notes":[0,0,0,0,2,0],"inversion":3,"playability":2,"extras":0},{"notes":[5,4,2,2,3,3],"inversion":1,"playability":2,"extras":1},{"notes":[5,5,2,2,2,3],"inversion":1,"playability":2,"extras":1},{"notes":[5,5,5,6,5,5],"inversion":1,"playability":2,"extras":1},{"notes":[12,12,12,12,14,12],"inversion":3,"playability":2,"extras":0},{"notes":[17,16,14,14,15,15],"inversion":1,"playability":2,"extras":1},{"notes":[17,17,14,14,14,15],"inversion":1,"playability":2,"extras":1},{"notes":[17,17,17,18,17,17],"inversion":1,"playability":2,"extras":1},{"notes":[0,0,0,0,2,3],"inversion":3,"playability":3,"extras":0},{"notes":[0,0,0,2,2,3],"inversion":3,"playability":3,"extras":3},{"notes":[5,5,5,6,5,9],"inversion":1,"playability":3,"extras":1},{"notes":[12,12,12,12,14,15],"inversion":3,"playability":3,"extras":0},{"notes":[12,12,12,14,14,15],"inversion":3,"playability":3,"extras":3},{"notes":[17,17,17,18,17,21],"inversion":1,"playability":3,"extras":1},{"notes":[3,4,2,2,3,3],"inversion":4,"playability":4,"extras":1},{"notes":[3,4,2,2,3,5],"inversion":4,"playability":4,"extras":0},{"notes":[3,5,2,2,2,3],"inversion":4,"playability":4,"extras":1},{"notes":[3,5,2,2,2,5],"inversion":4,"playability":4,"extras":0},{"notes":[5,5,5,9,8,9],"inversion":1,"playability":4,"extras":3},{"notes":[5,5,7,9,8,9],"inversion":1,"playability":4,"extras":3},{"notes":[9,10,12,9,10,9],"inversion":2,"playability":4,"extras":1},{"notes":[9,10,11,9,10,10],"inversion":2,"playability":4,"extras":1},{"notes":[10,10,11,9,10,9],"inversion":5,"playability":4,"extras":1},{"notes":[15,16,14,14,15,15],"inversion":4,"playability":4,"extras":1},{"notes":[15,16,14,14,15,17],"inversion":4,"playability":4,"extras":0},{"notes":[15,17,14,14,14,15],"inversion":4,"playability":4,"extras":1},{"notes":[15,17,14,14,14,17],"inversion":4,"playability":4,"extras":0},{"notes":[17,17,17,21,20,21],"inversion":1,"playability":4,"extras":3},{"notes":[17,17,19,21,20,21],"inversion":1,"playability":4,"extras":3},{"notes":[5,4,5,7,5,5],"inversion":1,"playability":5,"extras":3},{"notes":[9,10,12,9,10,10],"inversion":2,"playability":5,"extras":1},{"notes":[12,10,11,9,10,10],"inversion":3,"playability":5,"extras":1},{"notes":[10,10,11,9,10,10],"inversion":5,"playability":5,"extras":1},{"notes":[12,10,12,9,10,9],"inversion":3,"playability":5,"extras":1},{"notes":[10,10,12,9,10,9],"inversion":5,"playability":5,"extras":1},{"notes":[10,12,11,12,10,12],"inversion":5,"playability":5,"extras":0},{"notes":[12,10,14,14,14,10],"inversion":3,"playability":5,"extras":2},{"notes":[10,10,14,14,14,12],"inversion":5,"playability":5,"extras":2},{"notes":[10,10,12,14,14,12],"inversion":5,"playability":5,"extras":3},{"notes":[17,16,17,19,17,17],"inversion":1,"playability":5,"extras":3},{"notes":[3,0,0,0,2,0],"inversion":4,"playability":6,"extras":0},{"notes":[5,4,5,7,5,3],"inversion":1,"playability":6,"extras":1},{"notes":[3,4,7,7,5,3],"inversion":4,"playability":6,"extras":1},{"notes":[3,4,7,7,5,5],"inversion":4,"playability":6,"extras":3},{"notes":[3,4,5,7,5,5],"inversion":4,"playability":6,"extras":1},{"notes":[3,5,5,6,5,5],"inversion":4,"playability":6,"extras":3},{"notes":[5,5,5,7,5,9],"inversion":1,"playability":6,"extras":1}]}