{"version":1,"chords":[{"notes":[6,5,4,2,3,2],"inversion":1,"playability":2,"extras":0},{"notes":[5,5,4,3,3,2],"inversion":4,"playability":2,"extras":0},{"notes":[6,5,7,7,7,5],"inversion":1,"playability":2,"extras":3},{"notes":[5,5,8,7,7,5],"inversion":4,"playability":2,"extras":3},{"notes":[5,5,8,7,7,6],"inversion":4,"playability":2,"extras":1},{"notes":[5,5,7,7,7,6],"inversion":4,"playability":2,"extras":3},{"notes":[10,13,12,11,10,10],"inversion":2,"playability":2,"extras":3},{"notes":[10,12,12,11,11,10],"inversion":2,"playability":2,"extras":3},{"notes":[18,17,16,14,15,14],"inversion":1,"playability":2,"extras":0},{"notes":[17,17,16,15,15,14],"inversion":4,"playability":2,"extras":0},{"notes":[18,17,19,19,19,17],"inversion":1,"playability":2,"extras":3},{"notes":[17,17,20,19,19,17],"inversion":4,"playability":2,"extras":3},{"notes":[17,17,20,19,19,18],"inversion":4,"playability":2,"extras":1},{"notes":[17,17,19,19,19,18],"inversion":4,"playability":2,"extras":3},{"notes":[6,5,4,3,3,5],"inversion":1,"playability":3,"extras":1},{"notes":[5,5,4,3,3,6],"inversion":4,"playability":3,"extras":0},{"notes":[6,5,7,7,7,6],"inversion":1,"playability":3,"extras":3},{"notes":[6,5,8,7,7,5],"inversion":1,"playability":3,"extras":3},{"notes":[6,9,7,7,7,6],"inversion":1,"playability":3,"extras":3},{"notes":[14,12,12,11,11,14],"inversion":3,"playability":3,"extras":0},{"notes":[18,17,16,15,15,17],"inversion":1,"playability":3,"extras":1},{"notes":[17,17,16,15,15,18],"inversion":4,"playability":3,"extras":0},{"notes":[18,17,19,19,19,18],"inversion":1,"playability":3,"extras":3},{"notes":[18,17,20,19,19,17],"inversion":1,"playability":3,"extras":3},{"notes":[18,21,19,19,19,18],"inversion":1,"playability":3,"extras":3},{"notes":[5,5,4,3,3,5],"inversion":4,"playability":4,"extras":1},{"notes":[5,5,4,7,7,6],"inversion":4,"playability":4,"extras":3},{"notes":[10,9,7,7,7,6],"inversion":2,"playability":4,"extras":0},{"notes":[14,13,12,11,10,10],"inversion":3,"playability":4,"extras":0},{"notes":[14,12,12,11,11,10],"inversion":3,"playability":4,"extras":0},{"notes":[17,17,16,15,15,17],"inversion":4,"playability":4,"extras":1},{"notes":[17,17,16,19,19,18],"inversion":4,"playability":4,"extras":3},{"notes":[2,1,4,2,3,2],"inversion":3,"playability":5,"extras":3},{"notes":[2,1,4,3,3,5],"inversion":3,"playability":5,"extras":3},{"notes":[5,9,8,7,7,5],"inversion":4,"playability":5,"extras":0},{"notes":[5,9,7,7,7,6],"inversion":4,"playability":5,"extras":0},{"notes":[6,9,7,7,10,6],"inversion":1,"playability":5,"extras":0},{"notes":[14,13,16,14,15,14],"inversion":3,"playability":5,"extras":3},{"notes":[14,13,16,15,15,17],"inversion":3,"playability":5,"extras":3},{"notes":[17,21,20,19,19,17],"inversion":4,"playability":5,"extras":0},{"notes":[17,21,19,19,19,18],"inversion":4,"playability":5,"extras":0},{"notes":[2,1,0,2,3,2],"inversion":3,"playability":6,"extras":3},{"notes":[2,0,0,3,3,2],"inversion":3,"playability":6,"extras":3},{"notes":[5,9,8,7,7,6],"inversion":4,"playability":6,"extras":0},{"notes":[10,9,8,7,10,10],"inversion":2,"playability":6,"extras":0},{"notes":[10,9,7,7,11,10],"inversion":2,"playability":6,"extras":0},{"notes":[14,13,12,14,15,14],"inversion":3,"playability":6,"extras":3},{"notes":[14,12,12,15,15,14],"inversion":3,"playability":6,"extras":3}]}